pain_imputer/__init__.py
pain_imputer/imputer.py
pain_imputer-0.1.3.dist-info/licenses/LICENSE
pain_imputer-0.1.3.dist-info/METADATA
pain_imputer-0.1.3.dist-info/WHEEL
pain_imputer-0.1.3.dist-info/top_level.txt
pain_imputer-0.1.3.dist-info/RECORD
