Metadata-Version: 2.4
Name: pain-imputer
Version: 0.1.3
Summary: PAIN : A library for imputing missing values
Home-page: https://github.com/RajEshwariCodes/PAIN_Library
Author: Rajeshwari Mistri
Author-email: rajeshwarimistri11@gmail.com
Keywords: data-imputation missing-data machine-learning scikit-learn random-forest autoencoder mixed-dataset
Classifier: Programming Language :: Python :: 3
Classifier: License :: OSI Approved :: MIT License
Classifier: Operating System :: OS Independent
Classifier: Intended Audience :: Science/Research
Classifier: Intended Audience :: Developers
Classifier: Topic :: Scientific/Engineering :: Artificial Intelligence
Requires-Python: >=3.7
License-File: LICENSE
Requires-Dist: numpy==1.21.0
Requires-Dist: pandas==1.3.0
Requires-Dist: scikit-learn==1.0.0
Requires-Dist: tensorflow==2.10.0
Dynamic: author
Dynamic: author-email
Dynamic: classifier
Dynamic: description
Dynamic: description-content-type
Dynamic: home-page
Dynamic: keywords
Dynamic: license-file
Dynamic: requires-dist
Dynamic: requires-python
Dynamic: summary
